SpeedTorch/CPUCupyPinned.py
SpeedTorch/CPUTorchPinned.py
SpeedTorch/CUPYLive.py
SpeedTorch/GPUTorch.py
SpeedTorch/GenTorch.py
SpeedTorch/__init__.py
SpeedTorch-0.1.6.dist-info/LICENSE
SpeedTorch-0.1.6.dist-info/METADATA
SpeedTorch-0.1.6.dist-info/WHEEL
SpeedTorch-0.1.6.dist-info/top_level.txt
SpeedTorch-0.1.6.dist-info/RECORD
