Metadata-Version: 2.1
Name: SpeedTorch
Version: 0.1.6
Summary: Fast Pinned CPU -> GPU transfer
Home-page: https://github.com/Santosh-Gupta/SpeedTorch
Author: Santosh Gupta
Author-email: SanGupta.ML@gmail.com
License: MIT
Platform: UNKNOWN
Classifier: Programming Language :: Python :: 2.7
Classifier: Programming Language :: Python :: 3.6
Classifier: License :: OSI Approved :: MIT License
Classifier: Operating System :: OS Independent
Requires-Python: >=3.5.0
Requires-Dist: numpy
Requires-Dist: torch
